pygeodetics/Ellipsoid.py
pygeodetics/Geodetic.py
pygeodetics/__init__.py
pygeodetics/requirements.txt
pygeodetics/benchmarks/benchmarking.py
pygeodetics/geodetics/ECEF2enu.py
pygeodetics/geodetics/ECEF2geod.py
pygeodetics/geodetics/Mrad.py
pygeodetics/geodetics/Nrad.py
pygeodetics/geodetics/Vincenty.py
pygeodetics/geodetics/__init__.py
pygeodetics/geodetics/footpoint_latitude.py
pygeodetics/geodetics/geod2ECEF.py
pygeodetics/geodetics/geodetic_direct_problem.py
pygeodetics/geodetics/geodetic_inverse_problem.py
pygeodetics/geodetics/meridional_arc_dist.py
pygeodetics/geodetics/radius_of_curvature_azimuth.py
pygeodetics/projections/GridConvergence.py
pygeodetics/projections/MercatorVariantC.py
pygeodetics/projections/ScaleFactor.py
pygeodetics/projections/TransverseMercator.py
pygeodetics/projections/__init__.py
pygeodetics/utils/ProjectionZoneCalc.py
pygeodetics/utils/deg2dms.py
pygeodetics/utils/dms2deg.py
pygeodetics/utils/round_to_significant_digits.py
pygeodetics-0.1.0.dist-info/LICENSE
pygeodetics-0.1.0.dist-info/METADATA
pygeodetics-0.1.0.dist-info/WHEEL
pygeodetics-0.1.0.dist-info/top_level.txt
pygeodetics-0.1.0.dist-info/RECORD
