Metadata-Version: 2.2
Name: pygeodetics
Version: 0.1.0
Summary: A Python library for geodetic computations
Author-email: Per Helge Aarnes <per.helge.aarnes@gmail.com>
License: MIT License
Project-URL: Homepage, https://github.com/paarnes/pygeodetics
Project-URL: Repository, https://github.com/paarnes/pygeodetics
Project-URL: Issues, https://github.com/paarnes/pygeodetics/issues
Keywords: geodesy,coordinates,geodetic,ECEF,ENU,conversion,ellipsoid,geodetic-direct,geodetic-inverse,vincenty-formula,transverse-mercator,map-projections,scale-factor,grid-convergence
Classifier: Development Status :: 4 - Beta
Classifier: Intended Audience :: Developers
Classifier: License :: OSI Approved :: MIT License
Classifier: Programming Language :: Python :: 3
Classifier: Programming Language :: Python :: 3.7
Classifier: Programming Language :: Python :: 3.8
Classifier: Programming Language :: Python :: 3.9
Classifier: Programming Language :: Python :: 3.10
Classifier: Programming Language :: Python :: 3.11
Classifier: Programming Language :: Python :: 3.12
Requires-Python: >=3.7
License-File: LICENSE
Requires-Dist: numpy>=1.21
